tsontson_learn-0.2.2.dist-info/METADATA
tsontson_learn-0.2.2.dist-info/WHEEL
tsontson_learn/py.typed
tsontson_learn/__init__.py
tsontson_learn/tsontson_linear.py
tsontson_learn/__pycache__/tsontson_linear.cpython-312.pyc
tsontson_learn/__pycache__/_linear_regression.cpython-312.pyc
tsontson_learn/__pycache__/__init__.cpython-312.pyc
tsontson_learn/tsontson_learn.cpython-312-x86_64-linux-gnu.so
tsontson_learn-0.2.2.dist-info/RECORD
