Metadata-Version: 2.1
Name: tsontson_learn
Version: 0.2.2
Classifier: Programming Language :: Python
Classifier: Programming Language :: Rust
Classifier: Development Status :: 3 - Alpha
Classifier: Intended Audience :: Developers
Summary: A Python wrapper for the tsontson_learn Rust library
Keywords: linear-regression,rust,python
Author: Inzirillo & Genet (aka da sonsons)
License: MIT/Apache-2.0
